{"mc":{
	"pet2011_1r":{
		"frameRate":12,
		"frames":[
			{"res":"10009","x":-80,"y":-119},
			{"res":"10010","x":-86,"y":-121},
			{"res":"10011","x":-89,"y":-122},
			{"res":"10012","x":-92,"y":-176},
			{"res":"10013","x":-95,"y":-121},
			{"res":"10014","x":-94,"y":-123},
			{"res":"10015","x":-81,"y":-123},
			{"res":"10016","x":-79,"y":-122}
		]
}},
"res":{
	"10009":{"x":320,"y":140,"w":144,"h":144},
	"10010":{"x":160,"y":2,"w":150,"h":154},
	"10011":{"x":2,"y":212,"w":154,"h":154},
	"10012":{"x":2,"y":2,"w":156,"h":208},
	"10013":{"x":160,"y":158,"w":158,"h":134},
	"10014":{"x":312,"y":2,"w":158,"h":136},
	"10015":{"x":158,"y":294,"w":146,"h":134},
	"10016":{"x":320,"y":286,"w":144,"h":138}
}}