{"mc":{
	"Pweapon106_3o":{
		"frameRate":12,
		"frames":[
			{"res":"30035","x":-117,"y":-148},
			{"res":"30036","x":-119,"y":-148},
			{"res":"30037","x":-121,"y":-146},
			{"res":"30038","x":-121,"y":-142},
			{"res":"30039","x":-120,"y":-137},
			{"res":"30040","x":-120,"y":-137},
			{"res":"30041","x":-120,"y":-137},
			{"res":"30042","x":-118,"y":-139}
		]
}},
"res":{
	"30035":{"x":2,"y":132,"w":122,"h":126},
	"30036":{"x":2,"y":2,"w":124,"h":128},
	"30037":{"x":2,"y":632,"w":120,"h":128},
	"30038":{"x":2,"y":502,"w":120,"h":128},
	"30039":{"x":2,"y":884,"w":118,"h":124},
	"30040":{"x":2,"y":762,"w":120,"h":120},
	"30041":{"x":2,"y":382,"w":122,"h":118},
	"30042":{"x":2,"y":260,"w":122,"h":120}
}}