{"mc":{
	"weapon002_3s":{
		"frameRate":12,
		"frames":[
			{"res":"30001","x":-32,"y":-58},
			{"res":"30002","x":-32,"y":-59},
			{"res":"30003","x":-32,"y":-57},
			{"res":"30004","x":-32,"y":-58},
			{"res":"30005","x":-32,"y":-57},
			{"res":"30006","x":-33,"y":-58},
			{"res":"30007","x":-33,"y":-58},
			{"res":"30008","x":-33,"y":-59}
		]
}},
"res":{
	"30001":{"x":2,"y":572,"w":16,"h":92},
	"30002":{"x":2,"y":478,"w":16,"h":92},
	"30003":{"x":2,"y":666,"w":16,"h":90},
	"30004":{"x":2,"y":384,"w":16,"h":92},
	"30005":{"x":2,"y":290,"w":16,"h":92},
	"30006":{"x":2,"y":194,"w":16,"h":94},
	"30007":{"x":2,"y":98,"w":16,"h":94},
	"30008":{"x":2,"y":2,"w":16,"h":94}
}}