{"mc":{
	"weapon205_3r":{
		"frameRate":12,
		"frames":[
			{"res":"30009","x":-120,"y":-120},
			{"res":"30010","x":-121,"y":-110},
			{"res":"30011","x":-120,"y":-109},
			{"res":"30012","x":-120,"y":-109},
			{"res":"30013","x":-119,"y":-106},
			{"res":"30014","x":-118,"y":-106},
			{"res":"30015","x":-118,"y":-112},
			{"res":"30016","x":-119,"y":-118}
		]
}},
"res":{
	"30009":{"x":2,"y":2,"w":170,"h":108},
	"30010":{"x":348,"y":2,"w":172,"h":98},
	"30011":{"x":698,"y":2,"w":174,"h":90},
	"30012":{"x":1052,"y":2,"w":176,"h":84},
	"30013":{"x":1230,"y":2,"w":176,"h":80},
	"30014":{"x":874,"y":2,"w":176,"h":84},
	"30015":{"x":522,"y":2,"w":174,"h":92},
	"30016":{"x":174,"y":2,"w":172,"h":100}
}}