{"mc":{
	"weapon209g_3p":{
		"frameRate":12,
		"frames":[
			{"res":"30027","x":-61,"y":-161},
			{"res":"30028","x":-60,"y":-160},
			{"res":"30029","x":-59,"y":-159},
			{"res":"30030","x":-58,"y":-158},
			{"res":"30031","x":-59,"y":-158},
			{"res":"30032","x":-59,"y":-158},
			{"res":"30033","x":-59,"y":-159},
			{"res":"30034","x":-60,"y":-160}
		]
}},
"res":{
	"30027":{"x":2,"y":168,"w":38,"h":170},
	"30028":{"x":82,"y":168,"w":38,"h":168},
	"30029":{"x":82,"y":338,"w":38,"h":166},
	"30030":{"x":2,"y":340,"w":38,"h":164},
	"30031":{"x":44,"y":2,"w":40,"h":164},
	"30032":{"x":2,"y":2,"w":40,"h":164},
	"30033":{"x":42,"y":338,"w":38,"h":166},
	"30034":{"x":42,"y":168,"w":38,"h":168}
}}