{"mc":{
	"pet1051_1s":{
		"frameRate":12,
		"frames":[
			{"res":"10001","x":-145,"y":-143},
			{"res":"10002","x":-144,"y":-146},
			{"res":"10003","x":-143,"y":-147},
			{"res":"10004","x":-146,"y":-142},
			{"res":"10005","x":-149,"y":-137},
			{"res":"10006","x":-148,"y":-135},
			{"res":"10007","x":-146,"y":-135},
			{"res":"10008","x":-145,"y":-133}
		]
}},
"res":{
	"10001":{"x":634,"y":2,"w":206,"h":176},
	"10002":{"x":424,"y":2,"w":208,"h":176},
	"10003":{"x":214,"y":2,"w":208,"h":176},
	"10004":{"x":1268,"y":2,"w":212,"h":168},
	"10005":{"x":1482,"y":2,"w":216,"h":164},
	"10006":{"x":842,"y":2,"w":214,"h":172},
	"10007":{"x":2,"y":2,"w":210,"h":176},
	"10008":{"x":1058,"y":2,"w":208,"h":172}
}}