{"mc":{
	"pet1022_3r":{
		"frameRate":12,
		"frames":[
			{"res":"30009","x":-64,"y":-110},
			{"res":"30010","x":-64,"y":-114},
			{"res":"30011","x":-61,"y":-115},
			{"res":"30012","x":-58,"y":-113},
			{"res":"30013","x":-56,"y":-112},
			{"res":"30014","x":-57,"y":-113},
			{"res":"30015","x":-55,"y":-113},
			{"res":"30016","x":-59,"y":-112}
		]
}},
"res":{
	"30009":{"x":140,"y":2,"w":132,"h":156},
	"30010":{"x":2,"y":2,"w":136,"h":164},
	"30011":{"x":2,"y":168,"w":136,"h":154},
	"30012":{"x":274,"y":158,"w":130,"h":148},
	"30013":{"x":268,"y":308,"w":126,"h":144},
	"30014":{"x":140,"y":310,"w":126,"h":140},
	"30015":{"x":140,"y":160,"w":126,"h":148},
	"30016":{"x":274,"y":2,"w":128,"h":154}
}}