{"mc":{
	"pet1008_3r":{
		"frameRate":10,
		"events":[
			
			],
		"frames":[
			
			{
			"res":"31C5033E",
			"x":-161,
			"y":-111
			},
			{
			"res":"1A839F4A",
			"x":-161,
			"y":-112
			},
			{
			"res":"D153C104",
			"x":-161,
			"y":-114
			},
			{
			"res":"8D73E90F",
			"x":-160,
			"y":-114
			},
			{
			"res":"2DB47621",
			"x":-159,
			"y":-114
			}
			]
}},
	"res":{
		"8D73E90F":{"x":1,"y":490,"w":262,"h":120},
		"2DB47621":{"x":1,"y":124,"w":261,"h":121},
		"1A839F4A":{"x":1,"y":246,"w":263,"h":120},
		"31C5033E":{"x":1,"y":1,"w":262,"h":121},
		"D153C104":{"x":1,"y":368,"w":263,"h":120}
	}}