{"mc":{
	"pet1059_1s":{
		"frameRate":12,
		"events":[
			
			],
		"frames":[
			
			{
			"res":"78B5E6E8",
			"x":-133,
			"y":-203
			},
			{
			"res":"7239843A",
			"x":-123,
			"y":-204
			},
			{
			"res":"F5859AB1",
			"x":-125,
			"y":-200
			},
			{
			"res":"D00FE9B",
			"x":-127,
			"y":-200
			},
			{
			"res":"D9AF0007",
			"x":-127,
			"y":-199
			},
			{
			"res":"BD6CE635",
			"x":-129,
			"y":-201
			},
			{
			"res":"4EFBB767",
			"x":-132,
			"y":-202
			},
			{
			"res":"6C75FBED",
			"x":-133,
			"y":-202
			}
			]
}},
	"res":{
		"F5859AB1":{"x":287,"y":257,"w":281,"h":254},
		"78B5E6E8":{"x":1,"y":1,"w":282,"h":258},
		"7239843A":{"x":1,"y":515,"w":272,"h":259},
		"D9AF0007":{"x":568,"y":1,"w":283,"h":252},
		"4EFBB767":{"x":285,"y":1,"w":281,"h":254},
		"BD6CE635":{"x":567,"y":513,"w":279,"h":252},
		"D00FE9B":{"x":1,"y":261,"w":284,"h":252},
		"6C75FBED":{"x":287,"y":513,"w":278,"h":256}
	}}