{"mc":{
	"pet1005_1s":{
		"frameRate":12,
		"events":[
			
			],
		"frames":[
			
			{
			"res":"989C17B6",
			"x":-119,
			"y":-95
			},
			{
			"res":"40CD6061",
			"x":-117,
			"y":-97
			},
			{
			"res":"D44668D3",
			"x":-103,
			"y":-97
			},
			{
			"res":"678AA6CA",
			"x":-119,
			"y":-95
			},
			{
			"res":"3583F0A4",
			"x":-119,
			"y":-97
			},
			{
			"res":"8F4782DC",
			"x":-112,
			"y":-95
			}
			]
}},
	"res":{
		"678AA6CA":{"x":1,"y":126,"w":167,"h":121},
		"989C17B6":{"x":170,"y":1,"w":163,"h":121},
		"3583F0A4":{"x":1,"y":1,"w":167,"h":123},
		"D44668D3":{"x":335,"y":122,"w":149,"h":121},
		"40CD6061":{"x":335,"y":1,"w":163,"h":119},
		"8F4782DC":{"x":170,"y":124,"w":158,"h":123}
	}}