{"mc":{
	"pet1066_1s":{
		"frameRate":8,
		"events":[
			
			],
		"frames":[
			
			{
			"res":"72BE228A",
			"x":-70,
			"y":-195
			},
			{
			"res":"3B9D7FD0",
			"x":-72,
			"y":-193
			},
			{
			"res":"A6281977",
			"x":-72,
			"y":-191
			},
			{
			"res":"F7AAEC2B",
			"x":-71,
			"y":-188
			},
			{
			"res":"1001AF41",
			"x":-70,
			"y":-187
			},
			{
			"res":"6EB4D3AB",
			"x":-69,
			"y":-186
			},
			{
			"res":"E6C3AF2",
			"x":-67,
			"y":-188
			}
			]
}},
	"res":{
		"72BE228A":{"x":610,"y":231,"w":148,"h":230},
		"3B9D7FD0":{"x":458,"y":1,"w":149,"h":229},
		"F7AAEC2B":{"x":610,"y":1,"w":149,"h":227},
		"1001AF41":{"x":306,"y":1,"w":150,"h":228},
		"6EB4D3AB":{"x":153,"y":1,"w":151,"h":227},
		"E6C3AF2":{"x":1,"y":1,"w":150,"h":229},
		"A6281977":{"x":153,"y":231,"w":149,"h":227}
	}}