{"mc":{
	"attack":{
		"frameRate":8,
		"events":[
			
			],
		"frames":[
			
			{
			"res":"D1137761",
			"x":-83,
			"y":-152
			},
			{
			"res":"49652AFD",
			"x":-90,
			"y":-150
			},
			{
			"res":"C5B1F231",
			"x":-99,
			"y":-158
			},
			{
			"res":"4D5DEFC1",
			"x":-116,
			"y":-158
			},
			{
			"res":"BCD138A4",
			"x":-42,
			"y":-140
			},
			{
			"res":"61CEC212",
			"x":-98,
			"y":-138
			},
			{
			"res":"50EE200A",
			"x":-55,
			"y":-140
			},
			{
			"res":"30CE1011",
			"x":-67,
			"y":-148
			}
			]
}},
	"res":{
		"30CE1011":{"x":767,"y":1,"w":168,"h":187},
		"D1137761":{"x":751,"y":190,"w":126,"h":187},
		"4D5DEFC1":{"x":583,"y":1,"w":182,"h":175},
		"49652AFD":{"x":314,"y":188,"w":152,"h":171},
		"61CEC212":{"x":1,"y":1,"w":311,"h":195},
		"50EE200A":{"x":314,"y":1,"w":267,"h":185},
		"BCD138A4":{"x":879,"y":190,"w":131,"h":165},
		"C5B1F231":{"x":583,"y":178,"w":166,"h":175}
	}}