{"mc":{
	"pet4009_3s":{
		"frameRate":8,
		"events":[
			
			],
		"frames":[
			
			{
			"res":"931D32BB",
			"x":-111,
			"y":-232
			},
			{
			"res":"1A97B39E",
			"x":-111,
			"y":-232
			},
			{
			"res":"C4C97EF5",
			"x":-113,
			"y":-232
			},
			{
			"res":"A2586566",
			"x":-116,
			"y":-232
			},
			{
			"res":"18AD3899",
			"x":-121,
			"y":-232
			},
			{
			"res":"422F50CC",
			"x":-124,
			"y":-232
			},
			{
			"res":"99428DBA",
			"x":-123,
			"y":-232
			}
			]
}},
	"res":{
		"C4C97EF5":{"x":1,"y":282,"w":236,"h":279},
		"422F50CC":{"x":1,"y":1,"w":247,"h":279},
		"1A97B39E":{"x":475,"y":282,"w":234,"h":279},
		"931D32BB":{"x":239,"y":282,"w":234,"h":279},
		"99428DBA":{"x":250,"y":1,"w":246,"h":279},
		"A2586566":{"x":744,"y":1,"w":239,"h":279},
		"18AD3899":{"x":498,"y":1,"w":244,"h":279}
	}}