{"mc":{
	"pet1063_s":{
		"frameRate":12,
		"events":[
			
			],
		"frames":[
			
			{
			"res":"BF4D6D5D",
			"x":-194,
			"y":-196
			},
			{
			"res":"216F24CA",
			"x":-203,
			"y":-196
			},
			{
			"res":"6C6A73DF",
			"x":-208,
			"y":-204
			},
			{
			"res":"A39343B1",
			"x":-211,
			"y":-207
			},
			{
			"res":"8E95F22F",
			"x":-214,
			"y":-210
			},
			{
			"res":"AA01304C",
			"x":-218,
			"y":-210
			},
			{
			"res":"9CCEB73B",
			"x":-222,
			"y":-204
			},
			{
			"res":"457F9A93",
			"x":-224,
			"y":-192
			}
			]
}},
	"res":{
		"216F24CA":{"x":1291,"y":373,"w":406,"h":389},
		"9CCEB73B":{"x":1291,"y":1,"w":429,"h":370},
		"BF4D6D5D":{"x":1,"y":379,"w":394,"h":389},
		"457F9A93":{"x":397,"y":379,"w":427,"h":358},
		"8E95F22F":{"x":433,"y":1,"w":428,"h":376},
		"AA01304C":{"x":1,"y":1,"w":430,"h":376},
		"6C6A73DF":{"x":863,"y":376,"w":417,"h":374},
		"A39343B1":{"x":863,"y":1,"w":426,"h":373}
	}}