{"mc":{"attack":{"frameRate":12,"frames":[{"res":"30017","x":-35,"y":-117},{"res":"30018","x":-39,"y":-115},{"res":"30019","x":-35,"y":-111},{"res":"30020","x":-41,"y":-111},{"res":"30021","x":-41,"y":-111},{"res":"30022","x":-41,"y":-111},{"res":"30023","x":-39,"y":-109},{"res":"30024","x":-37,"y":-111}]},"hit":{"frameRate":1,"frames":[{"res":"30025","x":-54,"y":-100}]},"die":{"frameRate":1,"frames":[{"res":"30026","x":-44,"y":-30}]}},"res":{"30017":{"x":2,"y":2,"w":68,"h":120},"30018":{"x":154,"y":2,"w":76,"h":118},"30019":{"x":540,"y":2,"w":68,"h":114},"30020":{"x":392,"y":2,"w":74,"h":114},"30021":{"x":312,"y":2,"w":78,"h":114},"30022":{"x":232,"y":2,"w":78,"h":114},"30023":{"x":610,"y":2,"w":72,"h":112},"30024":{"x":468,"y":2,"w":70,"h":114},"30025":{"x":72,"y":2,"w":80,"h":118},"30026":{"x":684,"y":2,"w":108,"h":68}}}