{"mc":{
	"eff_ui_qzybui_001":{
		"frameRate":8,
		"frames":[
			{"res":"00","x":-86,"y":-101},
			{"res":"01","x":-84,"y":-102},
			{"res":"02","x":-86,"y":-102},
			{"res":"03","x":-85,"y":-101},
			{"res":"04","x":-87,"y":-98},
			{"res":"05","x":-86,"y":-98},
			{"res":"06","x":-86,"y":-96},
			{"res":"07","x":-86,"y":-97}
		]
}},
"res":{
	"00":{"x":2,"y":2,"w":170,"h":188},
	"01":{"x":174,"y":2,"w":168,"h":188},
	"02":{"x":516,"y":2,"w":168,"h":186},
	"03":{"x":344,"y":2,"w":170,"h":186},
	"04":{"x":1036,"y":2,"w":174,"h":182},
	"05":{"x":860,"y":2,"w":174,"h":182},
	"06":{"x":1212,"y":2,"w":172,"h":182},
	"07":{"x":686,"y":2,"w":172,"h":184}
}}