{"mc":{
	"skill1022":{
		"frameRate":15,
		"frames":[
			{"res":"10001","x":-120,"y":-138},
			{"res":"10002","x":-184,"y":-204},
			{"res":"10003","x":-190,"y":-211},
			{"res":"10004","x":-196,"y":-217},
			{"res":"10005","x":-153,"y":-168},
			{"res":"10006","x":-154,"y":-169},
			{"res":"10007","x":-155,"y":-170},
			{"res":"10008","x":-155,"y":-168}
		]
}},
"res":{
	"10001":{"x":2,"y":264,"w":306,"h":154},
	"10002":{"x":556,"y":2,"w":384,"h":236},
	"10003":{"x":248,"y":2,"w":306,"h":248},
	"10004":{"x":2,"y":2,"w":244,"h":260},
	"10005":{"x":796,"y":240,"w":152,"h":152},
	"10006":{"x":640,"y":240,"w":154,"h":154},
	"10007":{"x":310,"y":252,"w":158,"h":156},
	"10008":{"x":470,"y":252,"w":168,"h":154}
}}