{"mc":{
	"skill3004":{
		"frameRate":15,
		"frames":[
			{"res":"10001","x":-52,"y":-56},
			{"res":"10002","x":-52,"y":-48},
			{"res":"10003","x":-52,"y":-48},
			{"res":"10004","x":-53,"y":-44},
			{"res":"10005","x":-52,"y":-42},
			{"res":"10006","x":-49,"y":-41},
			{"res":"10007","x":-53,"y":-36},
			{"res":"10008","x":-48,"y":-34},
			{"res":"10009","x":-45,"y":-24}
		]
}},
"res":{
	"10001":{"x":2,"y":112,"w":118,"h":122},
	"10002":{"x":2,"y":650,"w":110,"h":102},
	"10003":{"x":2,"y":442,"w":112,"h":104},
	"10004":{"x":2,"y":2,"w":120,"h":108},
	"10005":{"x":2,"y":336,"w":114,"h":104},
	"10006":{"x":2,"y":548,"w":112,"h":100},
	"10007":{"x":2,"y":236,"w":118,"h":98},
	"10008":{"x":2,"y":754,"w":110,"h":72},
	"10009":{"x":2,"y":828,"w":108,"h":60}
},
"scale": 50}